ShynaJokes/ShynaJokes.py
ShynaJokes/__init__.py
ShynaJokes-0.0.2.dist-info/LICENSE
ShynaJokes-0.0.2.dist-info/METADATA
ShynaJokes-0.0.2.dist-info/WHEEL
ShynaJokes-0.0.2.dist-info/top_level.txt
ShynaJokes-0.0.2.dist-info/RECORD
