Metadata-Version: 2.1
Name: ShynaJokes
Version: 0.0.2
Summary: This package will provide Joke services.
Author: Shivam Sharma
Author-email: shivamsharma1913@gmail.com
License-File: LICENSE
Requires-Dist: requests
Requires-Dist: setuptools
Requires-Dist: wheel
